streamdeckui/__init__.py
streamdeckui/deck.py
streamdeckui/key.py
streamdeckui/mixins.py
streamdeckui/page.py
streamdeckui/periodic.py
streamdeckui/reify.py
streamdeckui/timers.py
streamdeckui/utils.py
streamdeckui/assets/Roboto-Regular.ttf
streamdeckui/assets/power.png
streamdeckui/assets/pressed.png
streamdeckui-0.0.4.dist-info/LICENSE.md
streamdeckui-0.0.4.dist-info/METADATA
streamdeckui-0.0.4.dist-info/WHEEL
streamdeckui-0.0.4.dist-info/top_level.txt
streamdeckui-0.0.4.dist-info/RECORD
